LICENSE
MANIFEST.in
README.md
setup.py
readgood/__init__.py
readgood/util.py
readgood/workflow.py
readgood.egg-info/PKG-INFO
readgood.egg-info/SOURCES.txt
readgood.egg-info/dependency_links.txt
readgood.egg-info/requires.txt
readgood.egg-info/top_level.txt
scripts/readgood
texts/hamlet.txt
texts/hamlet_full.txt
texts/testtext.txt