Metadata-Version: 1.0
Name: readgood
Version: 0.1.1
Summary: readgood
Home-page: https://github.com/wasade/readgood
Author: Daniel McDonald
Author-email: mcdonadt@colorado.edu
License: BSD
Platform: UNKNOWN
Classifier: Development Status :: 4 - Beta
Classifier: License :: OSI Approved :: BSD License
Classifier: Topic :: Multimedia :: Graphics :: Presentation
Classifier: Programming Language :: Python
Classifier: Programming Language :: Python :: 2.7
Classifier: Programming Language :: Python :: Implementation :: CPython
Classifier: Operating System :: OS Independent
Classifier: Operating System :: POSIX
Classifier: Operating System :: POSIX :: Linux
Classifier: Operating System :: MacOS :: MacOS X
